casegenmc/__init__.py
casegenmc/core.py
casegenmc/discretization_error.py
casegenmc/plotting_base.py
casegenmc/plotting_util.py
casegenmc/tex_plots.py
casegenmc/util.py
casegenmc/wrap_optimizers.py
casegenmc-0.1.19.dist-info/licenses/LICENSE
casegenmc-0.1.19.dist-info/METADATA
casegenmc-0.1.19.dist-info/WHEEL
casegenmc-0.1.19.dist-info/top_level.txt
casegenmc-0.1.19.dist-info/RECORD
