Metadata-Version: 2.4
Name: casegenmc
Version: 0.1.19
Summary: Case generator, optimizer, and summarizer for models.
Author-email: Lorenzo Venneri <lorenzo.venneri@gmail.com>
License: Copyright (c) 2018 The Python Packaging Authority
Project-URL: Homepage, https://github.com/lvenneri/casegenmc
Classifier: Programming Language :: Python :: 3.7
Classifier: License :: OSI Approved :: MIT License
Classifier: Operating System :: OS Independent
Requires-Python: >=3.7
License-File: LICENSE
Requires-Dist: numpy>=1.18.0
Requires-Dist: pandas>=1.0.0
Requires-Dist: matplotlib>=3.1.0
Requires-Dist: scipy>=1.4.0
Requires-Dist: plotly>=5.0.0
Requires-Dist: ray>=2.0.0
Requires-Dist: tqdm>=4.62.3
Requires-Dist: jinja2>=3.0.0
Dynamic: license-file
